pingos/__init__.py
pingos/cli.py
pingos/pingos.py
pingos-0.1.3.dist-info/LICENSE
pingos-0.1.3.dist-info/METADATA
pingos-0.1.3.dist-info/WHEEL
pingos-0.1.3.dist-info/entry_points.txt
pingos-0.1.3.dist-info/RECORD
