Metadata-Version: 2.3
Name: pingos
Version: 0.1.3
Summary: A TCP/UDP port ping client
Author: andrew.chang
Author-email: ultrasparc@naver.com
Requires-Python: >=3.8,<4.0
Classifier: Programming Language :: Python :: 3
Classifier: Programming Language :: Python :: 3.8
Classifier: Programming Language :: Python :: 3.9
Classifier: Programming Language :: Python :: 3.10
Classifier: Programming Language :: Python :: 3.11
Classifier: Programming Language :: Python :: 3.12
Classifier: Programming Language :: Python :: 3.13
Requires-Dist: click (==7.1.2)
Requires-Dist: rich (>=13.7.0,<14.0.0)
